printWithStyle/__init__.py
printWithStyle/print.py
printWithStyle-0.0.2.dist-info/LICENSE
printWithStyle-0.0.2.dist-info/METADATA
printWithStyle-0.0.2.dist-info/WHEEL
printWithStyle-0.0.2.dist-info/top_level.txt
printWithStyle-0.0.2.dist-info/RECORD
