Metadata-Version: 2.1
Name: printWithStyle
Version: 0.0.2
Summary: UNKNOWN
Home-page: https://github.com/lffelmann/printWithStyle
Author: lffelmann
License: UNKNOWN
Platform: UNKNOWN
Classifier: Programming Language :: Python :: 3
Classifier: License :: OSI Approved :: MIT License
Classifier: Operating System :: OS Independent
Requires-Python: >=3.6
License-File: LICENSE
